{"from":10001,"to":90001,"rating":9}
{"from":10001,"to":90002,"rating":3}
{"from":10001,"to":90003,"rating":9}
{"from":10002,"to":90001,"rating":8}
{"from":10002,"to":90002,"rating":7}
{"from":10002,"to":90003,"rating":5}
{"from":10002,"to":90004,"rating":7}
{"from":10002,"to":90005,"rating":9}
{"from":10002,"to":90006,"rating":8}
{"from":10006,"to":90005,"rating":4}
{"from":10006,"to":90006,"rating":9}
{"from":10001,"to":90001,"rating":5}
{"from":10001,"to":90002,"rating":6}
{"from":10001,"to":90003,"rating":7}
{"from":10001,"to":90004,"rating":8}
{"from":10004,"to":90003,"rating":3}
{"from":10004,"to":90004,"rating":7}
{"from":10004,"to":90005,"rating":9}